odoo9_addon_portal_partner_select_all-9.0.1.0.1.99.dev3-nspkg.pth
odoo_addons/portal_partner_select_all/README.rst
odoo_addons/portal_partner_select_all/__init__.py
odoo_addons/portal_partner_select_all/__openerp__.py
odoo_addons/portal_partner_select_all/i18n/portal_partner_select_all.pot
odoo_addons/portal_partner_select_all/readme/CONTRIBUTORS.rst
odoo_addons/portal_partner_select_all/readme/DESCRIPTION.rst
odoo_addons/portal_partner_select_all/readme/USAGE.rst
odoo_addons/portal_partner_select_all/static/description/icon.png
odoo_addons/portal_partner_select_all/static/description/index.html
odoo_addons/portal_partner_select_all/wizard/__init__.py
odoo_addons/portal_partner_select_all/wizard/portal_wizard.py
odoo_addons/portal_partner_select_all/wizard/portal_wizard.xml
odoo9_addon_portal_partner_select_all-9.0.1.0.1.99.dev3.dist-info/METADATA
odoo9_addon_portal_partner_select_all-9.0.1.0.1.99.dev3.dist-info/WHEEL
odoo9_addon_portal_partner_select_all-9.0.1.0.1.99.dev3.dist-info/namespace_packages.txt
odoo9_addon_portal_partner_select_all-9.0.1.0.1.99.dev3.dist-info/top_level.txt
odoo9_addon_portal_partner_select_all-9.0.1.0.1.99.dev3.dist-info/RECORD
