Metadata-Version: 2.1
Name: odoo9-addon-portal-partner-select-all
Version: 9.0.1.0.1.99.dev3
Summary: Portal Partner Select All
Home-page: https://www.github.com/OCA/partner-contact
Author: Tecnativa,Odoo Community Association (OCA)
Author-email: support@odoo-community.org
License: AGPL-3
Platform: UNKNOWN
Classifier: Programming Language :: Python
Classifier: Framework :: Odoo
Classifier: License :: OSI Approved :: GNU Affero General Public License v3
Requires-Python: ~=2.7
Requires-Dist: odoo (<9.1a,>=9.0a)
